[
  {
    "ID": "1",
    "idUsuario": "1",
    "idInstalacion": "1",
    "fecha": "01-01-2022",
    "hora": "09:00",
    "duracion": "60",
    "importe": "6"
  },
  {
    "ID": "2",
    "idUsuario": "1",
    "idInstalacion": "1",
    "fecha": "02-01-2022",
    "hora": "14:30",
    "duracion": "90",
    "importe": "9"
  },
  {
    "ID": "3",
    "idUsuario": "1",
    "idInstalacion": "2",
    "fecha": "03-01-2022",
    "hora": "10:00",
    "duracion": "60",
    "importe": "21"
  },
  {
    "ID": "4",
    "idUsuario": "1",
    "idInstalacion": "2",
    "fecha": "04-01-2022",
    "hora": "15:30",
    "duracion": "90",
    "importe": "21"
  },
  {
    "ID": "5",
    "idUsuario": "1",
    "idInstalacion": "3",
    "fecha": "05-01-2022",
    "hora": "11:00",
    "duracion": "60",
    "importe": "16"
  },
  {
    "ID": "6",
    "idUsuario": "1",
    "idInstalacion": "4",
    "fecha": "06-01-2022",
    "hora": "16:30",
    "duracion": "90",
    "importe": "16"
  },
  {
    "ID": "7",
    "idUsuario": "1",
    "idInstalacion": "5",
    "fecha": "07-01-2022",
    "hora": "12:30",
    "duracion": "60",
    "importe": "15"
  },
  {
    "ID": "8",
    "idUsuario": "1",
    "idInstalacion": "6",
    "fecha": "08-01-2022",
    "hora": "17:00",
    "duracion": "60",
    "importe": "15"
  },
  {
    "ID": "9",
    "idUsuario": "1",
    "idInstalacion": "7",
    "fecha": "09-01-2022",
    "hora": "13:00",
    "duracion": "60",
    "importe": "3"
  },
  {
    "ID": "10",
    "idUsuario": "1",
    "idInstalacion": "8",
    "fecha": "10-01-2022",
    "hora": "18:30",
    "duracion": "60",
    "importe": "15"
  },
  {
    "ID": "11",
    "idUsuario": "1",
    "idInstalacion": "1",
    "fecha": "11-01-2022",
    "hora": "14:00",
    "duracion": "60",
    "importe": "15"
  },
  {
    "ID": "12",
    "idUsuario": "1",
    "idInstalacion": "2",
    "fecha": "12-01-2022",
    "hora": "19:00",
    "duracion": "60",
    "importe": "15"
  },
  {
    "ID": "13",
    "idUsuario": "1",
    "idInstalacion": "3",
    "fecha": "13-01-2022",
    "hora": "15:00",
    "duracion": "60",
    "importe": "15"
  },
  {
    "ID": "14",
    "idUsuario": "1",
    "idInstalacion": "4",
    "fecha": "14-01-2022",
    "hora": "20:00",
    "duracion": "60",
    "importe": "15"
  },
  {
    "ID": "15",
    "idUsuario": "1",
    "idInstalacion": "5",
    "fecha": "15-01-2022",
    "hora": "16:00",
    "duracion": "60",
    "importe": "15"
  },
  {
    "ID": "16",
    "idUsuario": "1",
    "idInstalacion": "6",
    "fecha": "16-01-2022",
    "hora": "21:00",
    "duracion": "60",
    "importe": "15"
  },
  {
    "ID": "17",
    "idUsuario": "1",
    "idInstalacion": "7",
    "fecha": "17-01-2022",
    "hora": "17:00",
    "duracion": "60",
    "importe": "15"
  },
  {
    "ID": "18",
    "idUsuario": "1",
    "idInstalacion": "8",
    "fecha": "18-01-2022",
    "hora": "22:00",
    "duracion": "60",
    "importe": "15"
  },
  {
    "ID": "19",
    "idUsuario": "1",
    "idInstalacion": "1",
    "fecha": "19-01-2022",
    "hora": "18:00",
    "duracion": "60",
    "importe": "15"
  },
  {
    "ID": "20",
    "idUsuario": "1",
    "idInstalacion": "2",
    "fecha": "20-01-2022",
    "hora": "23:00",
    "duracion": "60",
    "importe": "15"
  }
]
